Compiled from "Demo2.java"
public class Demo2 {
  public Demo2();
    Code:
       0: aload_0
       1: invokespecial #1                  // Method java/lang/Object."<init>":()V
       4: return

  public static void _method$ben();
    Code:
       0: ldc           #2                  // String form ben
       2: invokestatic  #3                  // Method std/io.println:(Ljava/lang/String;)V
       5: return

  public static void main(java.lang.String[]);
    Code:
       0: new           #4                  // class processj/runtime/Scheduler
       3: dup
       4: invokespecial #5                  // Method processj/runtime/Scheduler."<init>":()V
       7: astore_1
       8: aload_1
       9: putstatic     #6                  // Field processj/runtime/PJProcess.scheduler:Lprocessj/runtime/Scheduler;
      12: new           #7                  // class Demo2$_proc$main
      15: dup
      16: aload_0
      17: invokespecial #8                  // Method Demo2$_proc$main."<init>":([Ljava/lang/String;)V
      20: invokevirtual #9                  // Method Demo2$_proc$main.schedule:()V
      23: getstatic     #6                  // Field processj/runtime/PJProcess.scheduler:Lprocessj/runtime/Scheduler;
      26: invokevirtual #10                 // Method processj/runtime/Scheduler.start:()V
      29: return
}
